tsktsk/__init__.py
tsktsk/__main__.py
tsktsk/config.py
tsktsk/task.py
tsktsk/commands/__init__.py
tsktsk/commands/base.py
tsktsk/commands/cli.py
tsktsk/repository/__init__.py
tsktsk/repository/file.py
tsktsk/repository/github.py
tsktsk-0.3.1.dist-info/LICENSE.md
tsktsk-0.3.1.dist-info/METADATA
tsktsk-0.3.1.dist-info/WHEEL
tsktsk-0.3.1.dist-info/entry_points.txt
tsktsk-0.3.1.dist-info/top_level.txt
tsktsk-0.3.1.dist-info/RECORD
