Metadata-Version: 2.1
Name: tsktsk
Version: 0.3.1
Summary: UNKNOWN
Home-page: UNKNOWN
Author: UNKNOWN
Author-email: UNKNOWN
License: UNKNOWN
Platform: UNKNOWN
Requires-Dist: certifi (==2020.6.20)
Requires-Dist: chardet (==3.0.4)
Requires-Dist: click (==7.1.2)
Requires-Dist: idna (==2.10)
Requires-Dist: python-dotenv (==0.14.0)
Requires-Dist: pyyaml (==5.3.1)
Requires-Dist: requests (==2.24.0)
Requires-Dist: six (==1.15.0)
Requires-Dist: smalld-click (==0.2.1)
Requires-Dist: smalld (==0.1.7)
Requires-Dist: typing-extensions (==3.7.4.2)
Requires-Dist: urllib3 (==1.25.9)
Requires-Dist: websocket-client (==0.57.0)
